ate/__init__.py
ate/__main__.py
ate/archiving.py
ate/test.py
ate/test_sequence.py
ate/version.py
ate-0.27.0.dist-info/METADATA
ate-0.27.0.dist-info/WHEEL
ate-0.27.0.dist-info/license.txt
ate-0.27.0.dist-info/top_level.txt
ate-0.27.0.dist-info/RECORD
