Metadata-Version: 2.1
Name: ate
Version: 0.27.0
Summary: Automated Test Environment, a framework for building device testing quickly and consistently
Home-page: https://github.com/slightlynybbled/ate
Author: Jason R. Jones
Author-email: slightlynybbled@gmail.com
License: MIT
Platform: UNKNOWN
Classifier: License :: OSI Approved :: MIT License
Classifier: Development Status :: 3 - Alpha
Classifier: Programming Language :: Python
Classifier: Programming Language :: Python :: 3
Classifier: Programming Language :: Python :: 3.6
Classifier: Programming Language :: Python :: 3.7
Classifier: Programming Language :: Python :: Implementation :: CPython
Requires-Python: >=3.6.0
Requires-Dist: coloredlogs (>=10.0)
